[
    {
    "firstname":"Kevin",
    "height":180,
    "email":"Kevin@gmail.com",
    "city":{
        "mailing address":"Taipei",
        "Residence address":"Taoyuan"
    },
    "phone":{
        "Local calls":"02-29881055",
        "cellphone number":"0933-852177"
    },
    "cars":["BMW", "Nissan GT-R", "Audi"]
    },

    {
    "firstname":"Jeff",
    "height":182,
    "email":"Jeff@gmail.com",
    "city":{
        "mailing address":"Taipei",
        "Residence address":"Taoyuan"
    },
    "phone":{
        "Local calls":"02-29881066",
        "cellphone number":"0933-852187"
    },
    "cars":["BMW", "Nissan GT-R", "Toyota"]
    },

    {
    "firstname":"Bill",
    "height":175,
    "email":"Billn@gmail.com",
    "city":{
        "mailing address":"Taipei",
        "Residence address":"Taoyuan"
    },
    "phone":{
        "Local calls":"02-29822055",
        "cellphone number":"0933-853177"
    },
    "cars":["BMW", "Nissan GT-R", "Audi"]}
]